LICENSE
MANIFEST.in
README.rst
setup.py
django_riak_sessions.egg-info/PKG-INFO
django_riak_sessions.egg-info/SOURCES.txt
django_riak_sessions.egg-info/dependency_links.txt
django_riak_sessions.egg-info/requires.txt
django_riak_sessions.egg-info/top_level.txt
riak_sessions/__init__.py
riak_sessions/models.py
riak_sessions/tests.py
riak_sessions/backends/__init__.py
riak_sessions/backends/riak.py