Metadata-Version: 1.0
Name: django-riak-sessions
Version: 0.0.4
Summary: Riak session backend for django
Home-page: http://github.com/flashingpumpkin/django-riak-sessions
Author: Alen Mujezinovic
Author-email: flashingpumpkin@gmail.com
License: UNKNOWN
Keywords: django riak session backend
Platform: UNKNOWN
Classifier: Development Status :: 4 - Beta
Classifier: Intended Audience :: Developers
Classifier: Topic :: Software Development :: Libraries :: Python Modules
Classifier: Environment :: Web Environment
Classifier: Topic :: Internet
Classifier: Operating System :: OS Independent
Classifier: Programming Language :: Python
Classifier: Framework :: Django
